Metadata-Version: 1.1
Name: aioworkers-amqp
Version: 0.1.0
Summary: Module for working with amqp broker
Home-page: https://github.com/aioworkers/aioworkers-amqp
Author: Alexander Malev
Author-email: yttrium@somedev.ru
License: Apache Software License 2.0
Keywords: aioworkers redis
Platform: UNKNOWN
Classifier: Development Status :: 2 - Pre-Alpha
Classifier: Intended Audience :: Developers
Classifier: License :: OSI Approved :: Apache Software License
Classifier: Programming Language :: Python :: 3
Classifier: Programming Language :: Python :: 3.5
Classifier: Programming Language :: Python :: 3.6
